[
  {
    "id": "D001",
    "name": "Groovy Grove",
    "bannedHero": [
      "H001",
      "H004",
      "H007",
      "H010"
    ],
    "seed": 784,
    "type": "regular",
    "eventLetter": "E014"
  },
  {
    "id": "D002",
    "name": "Spooky Spot",
    "bannedHero": [
      "H002",
      "H005",
      "H008",
      "H011"
    ],
    "seed": 7576,
    "type": "regular",
    "eventLetter": "E015"
  },
  {
    "id": "D003",
    "name": "Creepy Crag",
    "bannedHero": [
      "H003",
      "H006",
      "H009",
      "H012"
    ],
    "seed": 7236,
    "type": "regular",
    "eventLetter": "E016"
  },
  {
    "id": "D010",
    "name": "Boss I",
    "bannedHero": [
      "H001",
      "H004",
      "H007",
      "H010"
    ],
    "seed": 0,
    "type": "boss",
    "eventLetter": "E013"
  },
  {
    "id": "D011",
    "name": "Boss II",
    "bannedHero": [
      "H002",
      "H005",
      "H008",
      "H011"
    ],
    "seed": 0,
    "type": "boss",
    "eventLetter": "E013"
  },
  {
    "id": "D012",
    "name": "Boss III",
    "bannedHero": [
      "H003",
      "H006",
      "H009",
      "H012"
    ],
    "seed": 0,
    "type": "boss",
    "eventLetter": "E013"
  },
  {
    "id": "D013",
    "name": "Boss IV",
    "bannedHero": [
      "H001",
      "H004",
      "H007",
      "H010"
    ],
    "seed": 0,
    "type": "boss",
    "eventLetter": "E013"
  },
  {
    "id": "D014",
    "name": "Boss V",
    "bannedHero": [
      "H002",
      "H005",
      "H008",
      "H011"
    ],
    "seed": 0,
    "type": "boss",
    "eventLetter": "E013"
  },
  {
    "id": "D015",
    "name": "Boss VI",
    "bannedHero": [
      "H003",
      "H006",
      "H009",
      "H012"
    ],
    "seed": 0,
    "type": "boss",
    "eventLetter": "E013"
  },
  {
    "id": "D016",
    "name": "Boss VII",
    "bannedHero": [
      "H001",
      "H004",
      "H007",
      "H010"
    ],
    "seed": 0,
    "type": "boss",
    "eventLetter": "E013"
  },
  {
    "id": "D017",
    "name": "Boss VIII",
    "bannedHero": [
      "H002",
      "H005",
      "H008",
      "H011"
    ],
    "seed": 0,
    "type": "boss",
    "eventLetter": "E013"
  },
  {
    "id": "D018",
    "name": "Boss IX",
    "bannedHero": [
      "H003",
      "H006",
      "H009",
      "H012"
    ],
    "seed": 0,
    "type": "boss",
    "eventLetter": "E013"
  },
  {
    "id": "D019",
    "name": "Boss X",
    "bannedHero": [
      "H001",
      "H004",
      "H007",
      "H010"
    ],
    "seed": 0,
    "type": "boss",
    "eventLetter": "E013"
  }
]