[
  {
    "id": "S0000",
    "name": "Attack",
    "description": "A standard attack.",
    "icon": "<i class=\"fas fa-swords\"></i>",
    "targetEnemies": true,
    "powMod": 1,
    "techMod": 0,
    "bText": "#ATTACKER# attacks #DEFENDER# for #DAMAGE# damage"
  },
  {
    "id": "S0010",
    "name": "Reinforce",
    "description": "Increases armor for next two times being hit.",
    "icon": "<i class=\"fas fa-shield-cross\"></i>",
    "targetEnemies": false,
    "powMod": 0,
    "techMod": 0,
    "bText": "#ATTACKER# braces himself"
  },
  {
    "id": "S0020",
    "name": "Toughen",
    "description": "Increases maxHP and heals for the same amount",
    "icon": "<i class=\"fas fa-helmet-battle\"></i>",
    "targetEnemies": false,
    "powMod": 1,
    "techMod": 1,
    "bText": "#ATTACKER# increases his HP by #DAMAGE#"
  },
  {
    "id": "S1010",
    "name": "Meteor",
    "description": "Attacks all enemies and applies the scorched debuff. Enemies with the scorched debuff take damage every turn",
    "icon": "<i class=\"fas fa-fire\"></i>",
    "targetEnemies": true,
    "powMod": 1,
    "techMod": 1.5,
    "bText": "#ATTACKER# launches a meteor strike on all enemies"
  },
  {
    "id": "S1020",
    "name": "Frost Strike",
    "description": "Attacks and applies a chilled effect. If the target already has the chilled effect, increase the damage by 2.5x",
    "icon": "<i class=\"fas fa-snowflake\"></i>",
    "targetEnemies": true,
    "powMod": 1,
    "techMod": 1.5,
    "bText": "#ATTACKER# shoots a frosty blast towards #DEFENDER# for #DAMAGE# damage"
  },
  {
    "id": "S2010",
    "name": "Inspire",
    "description": "Inspires all teammates, increasing their Tech for the next two skills",
    "icon": "<i class=\"fas fa-lightbulb\"></i>",
    "targetEnemies": false,
    "powMod": 1,
    "techMod": 1,
    "bText": "#ATTACKER# inspires his teammates"
  },
  {
    "id": "S2030",
    "name": "Double Tap",
    "description": "Attacks twice in the same round.",
    "icon": "<i class=\"fas fa-fist-raised\"></i>",
    "targetEnemies": true,
    "powMod": 1,
    "techMod": 0,
    "bText": "#ATTACKER# launches a super attack against #DEFENDER# for #DAMAGE# damage"
  },
  {
    "id": "SM100",
    "name": "Swift Strike",
    "description": "Attacks the enemy and heals for the same amount.",
    "icon": "<i class=\"fab fa-swift\"></i>",
    "targetEnemies": true,
    "powMod": 2,
    "techMod": 0,
    "bText": "#ATTACKER# strikes #DEFENDER# for #DAMAGE# damage and heals the same amount"
  },
  {
    "id": "SM101",
    "name": "Regenerate",
    "description": "Heals self instead of attacking",
    "icon": "<i class=\"fas fa-heart-circle\"></i>",
    "targetEnemies": false,
    "powMod": 4,
    "techMod": 0,
    "bText": "#ATTACKER# heals itself"
  },
  {
    "id": "SM200",
    "name": "Translucent",
    "description": "Negates damage taken next time being hit.",
    "icon": "<i class=\"fas fa-ghost\"></i>",
    "targetEnemies": false,
    "powMod": 1,
    "techMod": 0,
    "bText": "#ATTACKER# turns transparent"
  },
  {
    "id": "SM201",
    "name": "Purge",
    "description": "Removes all debuffs from allies and damages for each debuff removed",
    "icon": "<i class=\"fas fa-broom\"></i>",
    "targetEnemies": true,
    "powMod": 1,
    "techMod": 0,
    "bText": "#ATTACKER# purges his allies of buffs and lets out an attack for #DAMAGE# damage"
  },
  {
    "id": "SM300",
    "name": "Lasers",
    "description": "Deal a powerful magical attack to the enemy.",
    "icon": "<i class=\"fas fa-scanner\"></i>",
    "targetEnemies": true,
    "powMod": 3,
    "techMod": 0,
    "bText": "#ATTACKER# lets out a powerful laser attack"
  },
  {
    "id": "SM301",
    "name": "Crab Hammer",
    "description": "Attacks for 25% of max HP of defender",
    "icon": "<i class=\"fas fa-hammer\"></i>",
    "targetEnemies": true,
    "powMod": 0,
    "techMod": 0,
    "bText": "#ATTACKER# whips out his crab hammer"
  },
  {
    "id": "SM901",
    "name": "Tree Wallop",
    "description": "High damage attack to second in order",
    "icon": "<i class=\"fas fa-tree\"></i>",
    "targetEnemies": true,
    "powMod": 7,
    "techMod": 0,
    "bText": "#ATTACKER# trees #DEFENDER# for #DAMAGE# damage"
  },
  {
    "id": "SM902",
    "name": "Phoenix Fire",
    "description": "Burns the first enemy, dealing damage for every stack",
    "icon": "<i class=\"fas fa-fire-alt\"></i>",
    "targetEnemies": true,
    "powMod": 0.14,
    "techMod": 0,
    "bText": "#ATTACKER# burns #DEFENDER#"
  },
  {
    "id": "SM902A",
    "name": "Hibernate",
    "description": "Monster is sleeping and performs no action",
    "icon": "<i class=\"fas fa-snooze\"></i>",
    "targetEnemies": false,
    "powMod": 0,
    "techMod": 0,
    "bText": "#ATTACKER# seems to be hibernating"
  },
  {
    "id": "SM902B",
    "name": "Rise",
    "description": "Monster returns to its original form",
    "icon": "<i class=\"fas fa-heartbeat\"></i>",
    "targetEnemies": false,
    "powMod": 0,
    "techMod": 0,
    "bText": [
      "The egg has hatched",
      ""
    ]
  },
  {
    "id": "SMP902",
    "name": "Rising Phoenix",
    "description": "Once below 25%, Phoenix will turn into an egg and attempt to regenerate health",
    "icon": "<i class=\"fab fa-phoenix-framework\"></i>",
    "targetEnemies": true,
    "powMod": 0,
    "techMod": 0,
    "bText": null
  }
]