[
  {
    "id": "rep",
    "title": "Reputation",
    "description": "Used to level up guilds.",
    "icon": "<i class=\"far fa-grin-alt\"></i>",
    "type": "static"
  },
  {
    "id": "in_inventory",
    "title": "In Inventory",
    "description": "Amount currently in your inventory.",
    "icon": "<i class=\"fas fa-cube\"></i>",
    "type": "static"
  },
  {
    "id": "hp",
    "title": "Health",
    "description": "The amount of damage an entity can sustain before being downed.",
    "icon": "<i class=\"fas fa-heart statHP\"></i>",
    "type": "static"
  },
  {
    "id": "pow",
    "title": "Power",
    "description": "The amount of damage an entity is capable of dealing.",
    "icon": "<i class=\"fad fa-sword statPOW\"></i>",
    "type": "static"
  },
  {
    "id": "spower",
    "title": "Special Power",
    "description": "The amount of damage an entity can deal with special attacks.",
    "icon": "<i class=\"fas fa-book-spells statSPOW\"></i>",
    "type": "static"
  },
  {
    "id": "armor",
    "title": "Armor",
    "description": "The damage resistance an entity possesses.",
    "icon": "<i class=\"fas fa-shield statARMOR\"></i>",
    "type": "static"
  },
  {
    "id": "crit",
    "title": "Critical Chance",
    "description": "The chance an entity will deal bonus damage on attack.",
    "icon": "<i class=\"fas fa-dagger statCRIT\"></i>",
    "type": "static"
  },
  {
    "id": "dodge",
    "title": "Dodge",
    "description": "The chance an entity will avoid an attack.",
    "icon": "<i class=\"fas fa-hood-cloak statDODGE\"></i>",
    "type": "static"
  },
  {
    "id": "clear_save",
    "title": "Clear Saved Game Data",
    "description": "Permanently delete your current saved game data. This action is irreversible.",
    "icon": "<i class=\"fas fa-file-times\"></i>",
    "type": "static"
  },
  {
    "id": "import_save",
    "title": "Import Game Data",
    "description": "Export your current game data for sharing or importing at a later time.",
    "icon": "<i class=\"fas fa-file-export\"></i>",
    "type": "static"
  },
  {
    "id": "export_save",
    "title": "Export Game Data",
    "description": "Import your own previously exported data or shared game data.",
    "icon": "<i class=\"fas fa-file-import\"></i>",
    "type": "static"
  },
  {
    "id": "cloud_save",
    "title": "Save or Load from Cloud",
    "description": "Save or load your game data from the Cloud using Playfab.",
    "icon": "<i class=\"fas fa-cloud-download\"></i>",
    "type": "static"
  },
  {
    "id": "settings",
    "title": "Settings",
    "description": "Change your game preferences and settings.",
    "icon": "<i class=\"fas fa-cog\"></i>",
    "type": "static"
  },
  {
    "id": "debug",
    "title": "Development Options",
    "description": "Development and debugging options for testing various mechanics and features.",
    "icon": "<i class=\"fas fa-bug\"></i>",
    "type": "static"
  },
  {
    "id": "crafting_time",
    "title": "Crafting Time",
    "description": "The amount of time needed to craft this recipe.",
    "icon": "<i class=\"fas fa-clock\"></i>",
    "type": null
  },
  {
    "id": "recipe_gold",
    "title": "#value# Gold",
    "description": "The amount of gold this recipe is worth.",
    "icon": "/images/resources/M001.png",
    "type": "recipe"
  },
  {
    "id": "fuse_time",
    "title": "Fuse Time",
    "description": "The amount of time needed to complete the fusion of this recipe.",
    "icon": "<i class=\"fas fa-clock\"></i>",
    "type": null
  },
  {
    "id": "material_desc",
    "title": "#name#",
    "description": "#description#</br>You have #amt#",
    "icon": "/images/resources/#id#.png",
    "type": "material"
  },
  {
    "id": "guild_worker",
    "title": "#name#",
    "description": "Represents a worker for the guild.",
    "icon": "/images/resources/#id#.png",
    "type": "guild"
  },
  {
    "id": "autosell_none",
    "title": "Auto-Sell Setting: None",
    "description": "You are currently not autoselling any of this item.",
    "icon": null,
    "type": null
  },
  {
    "id": "autosell_common",
    "title": "Auto-Sell Setting: Common",
    "description": "You are currently autoselling common quality for this item.",
    "icon": null,
    "type": null
  },
  {
    "id": "autosell_good",
    "title": "Auto-Sell Setting: Good and below",
    "description": "You are currently autoselling good and common quality for this item.",
    "icon": null,
    "type": null
  },
  {
    "id": "autosell_great",
    "title": "Auto-Sell Setting: Great and below",
    "description": "You are currently autoselling great, good and common quality for this item.",
    "icon": null,
    "type": null
  },
  {
    "id": "autosell_epic",
    "title": "Auto-Sell Setting: All",
    "description": "You are currently autoselling all qualities of this item.",
    "icon": null,
    "type": null
  },
  {
    "id": "R11001",
    "title": "Water Staff",
    "description": "Expert water staff users can use floods in expertly timed, awe inspiring bursts of magic.",
    "icon": null,
    "type": null
  },
  {
    "id": "R11002",
    "title": "Actor Rod",
    "description": "Technically it's a Barista Rod, but as long as the dream is still alive, I guess it counts.",
    "icon": null,
    "type": null
  },
  {
    "id": "R11003",
    "title": "Hate Wand",
    "description": "Most wizards use this wand out of anger, which unsurprisingly leads to suffering.",
    "icon": null,
    "type": null
  },
  {
    "id": "R11004",
    "title": "Heart Staff",
    "description": "Honestly the weirdest of the staves, and kind of a boring superpower.",
    "icon": null,
    "type": null
  },
  {
    "id": "R11005",
    "title": "Stewart Rod",
    "description": "Some rods have all the luck, and the Stewart Rod gets all the breaks.",
    "icon": null,
    "type": null
  },
  {
    "id": "R11006",
    "title": "Thunder Wand",
    "description": "Speaking scientifically, it's probably lightning, but the person who named it wasn't that bright.",
    "icon": null,
    "type": null
  },
  {
    "id": "R11007",
    "title": "Lunar Staff",
    "description": "Possibly fake.  It casts an odd shadow.  Could be a movie studio knockoff.",
    "icon": null,
    "type": null
  },
  {
    "id": "R11008",
    "title": "Love Wand",
    "description": "Romantic comedies are right: trading in glasses for contacts counts as a total makeover.",
    "icon": null,
    "type": null
  },
  {
    "id": "R11009",
    "title": "Fishing Rod",
    "description": "Don't teach a man to fish, feed yourself.  Fishing isn't that hard.",
    "icon": null,
    "type": null
  },
  {
    "id": "R11010",
    "title": "Janitorial Staff",
    "description": "Janitorial Staves may be underappreciated, but befriend them early and often.",
    "icon": null,
    "type": null
  },
  {
    "id": "R13001",
    "title": "Knife",
    "description": "Even the mighty oak starts as a simple acorn.",
    "icon": null,
    "type": null
  },
  {
    "id": "R13002",
    "title": "El Bow",
    "description": "Named by someone who took too many hits to their funny bone.",
    "icon": null,
    "type": null
  },
  {
    "id": "R13003",
    "title": "Cool Whip",
    "description": "This is a dish best served cold.",
    "icon": null,
    "type": null
  },
  {
    "id": "R13004",
    "title": "Butter Knife",
    "description": "Check out the low calorie version -- Hard To Believe This Isn't A Butter Knife.",
    "icon": null,
    "type": null
  },
  {
    "id": "R13005",
    "title": "Rain Bow",
    "description": "Now you can shoot enemies with all the colors of the wind.",
    "icon": null,
    "type": null
  },
  {
    "id": "R13006",
    "title": "Shaped Whip",
    "description": "Try to detect this whip, not before it's too late, or else you'll get whipped good.",
    "icon": null,
    "type": null
  },
  {
    "id": "R13007",
    "title": "Club Knife",
    "description": "It's the most exclusive Club in town.",
    "icon": null,
    "type": null
  },
  {
    "id": "R13008",
    "title": "Disintegrator",
    "description": "This bow is unlicensed.  I'd stand back if I were you.",
    "icon": null,
    "type": null
  },
  {
    "id": "R13009",
    "title": "Qilinbian",
    "description": "The qilinbian is mostly used for exercise, but certain instructors can wield it with lethal force.",
    "icon": null,
    "type": null
  },
  {
    "id": "R13010",
    "title": "The Bloopinator",
    "description": "This magical knife can slay overlords and tyrants, but using it comes with a price.",
    "icon": null,
    "type": null
  },
  {
    "id": "R12001",
    "title": "Meager Sword",
    "description": "Use it.  Abuse it.  Lose it.  That's the Meager Sword Motto.",
    "icon": null,
    "type": null
  },
  {
    "id": "R12002",
    "title": "Greedy Pickaxe",
    "description": "I'm not saying it's a gold digger, but it has been used in such activities in the past.",
    "icon": null,
    "type": null
  },
  {
    "id": "R12003",
    "title": "Striped Club",
    "description": "When used as a scratching post, it brings out all the cats and kittens.",
    "icon": null,
    "type": null
  },
  {
    "id": "R12004",
    "title": "Buzzblade",
    "description": "Set this blade to stun, instead of kill, and have a blast.",
    "icon": null,
    "type": null
  },
  {
    "id": "R12005",
    "title": "Gluttonous Axe",
    "description": "Gluttonous Axe is not very balanced, and probably should lose some weight around the belly.",
    "icon": null,
    "type": null
  },
  {
    "id": "R12006",
    "title": "Night Club",
    "description": "Nothing good ever happens with this club after two in the morning, so be careful.",
    "icon": null,
    "type": null
  },
  {
    "id": "R12007",
    "title": "Salty Sword",
    "description": "A weapon for the eternally angry and margarita fans alike.",
    "icon": null,
    "type": null
  },
  {
    "id": "R12008",
    "title": "Wrath",
    "description": "This axe's name varies by region. In some places it is known as Crusade, and in others, Cataclysm.",
    "icon": null,
    "type": null
  },
  {
    "id": "R12009",
    "title": "Knife Club",
    "description": "It's the most exclusive Knife in town.",
    "icon": null,
    "type": null
  },
  {
    "id": "R12010",
    "title": "Balmungous",
    "description": "Having two or three of these in a group will make a giant difference.",
    "icon": null,
    "type": null
  },
  {
    "id": "R2101",
    "title": "Standard Helmet",
    "description": "A plain, standard issue helmet given to soldiers on their way to war.",
    "icon": null,
    "type": null
  },
  {
    "id": "R2102",
    "title": "Cobalt Helmet",
    "description": "This helmet is extremely heat resistant, but it is also highly magnetic.",
    "icon": null,
    "type": null
  },
  {
    "id": "R2103",
    "title": "Regular Helmet",
    "description": "It does a much better job of preventing brain injuries than a rusty bucket ever could.",
    "icon": null,
    "type": null
  },
  {
    "id": "R2104",
    "title": "Super Helmet",
    "description": "Be grateful that this one doesn't come with that super annoying regional lockout.",
    "icon": null,
    "type": null
  },
  {
    "id": "R2105",
    "title": "Mega Helmet",
    "description": "This reactive armor says it reduces damage by 93%, but it's probably just marketing hype.",
    "icon": null,
    "type": null
  },
  {
    "id": "R2106",
    "title": "Skull Helmet",
    "description": "Forged from the skull of a giant insect, this helmet smells like jerky and deception.",
    "icon": null,
    "type": null
  },
  {
    "id": "R2107",
    "title": "Dark Helmet",
    "description": "Crafting this helmet always feels like the first time, for the last time.",
    "icon": null,
    "type": null
  },
  {
    "id": "R2108",
    "title": "Whimsical Helmet",
    "description": "The ideal helmet for stunt performers and clowns alike.",
    "icon": null,
    "type": null
  },
  {
    "id": "R2109",
    "title": "Magnetized Helmet",
    "description": "The metal in this helmet has been altered at the molecular level.",
    "icon": null,
    "type": null
  },
  {
    "id": "R2110",
    "title": "Coal Helmut",
    "description": "The perfect head cover for mine shafts and reunification.",
    "icon": null,
    "type": null
  },
  {
    "id": "R2201",
    "title": "Simple Hat",
    "description": "As long as it covers my bald spot, I'm happy.",
    "icon": null,
    "type": null
  },
  {
    "id": "R2202",
    "title": "Princess Tiara",
    "description": "This tiara isn't for real princesses, but rather those who demand to be treated like one.",
    "icon": null,
    "type": null
  },
  {
    "id": "R2203",
    "title": "Black Hat",
    "description": "It also comes in \"morally grey.\"",
    "icon": null,
    "type": null
  },
  {
    "id": "R2204",
    "title": "Beach Hat",
    "description": "This hat is perfect for summer days, where the sand is coarse, rough and irritating.",
    "icon": null,
    "type": null
  },
  {
    "id": "R2205",
    "title": "Green Bay Beret",
    "description": "It is made of foam, smells like beer, and comes with a warning against bears, vikings, and lions.",
    "icon": null,
    "type": null
  },
  {
    "id": "R2206",
    "title": "The Mind Cap",
    "description": "Concealed inside the lining is a healthy dose of tin foil, for obvious reasons.",
    "icon": null,
    "type": null
  },
  {
    "id": "R2207",
    "title": "Ornate Crown",
    "description": "Clearly overcompensating for something.",
    "icon": null,
    "type": null
  },
  {
    "id": "R2208",
    "title": "Spellcasting Hat",
    "description": "To awaken it's power, recite the following spell --  \"Lorem ipsum dolor sit amet\"",
    "icon": null,
    "type": null
  },
  {
    "id": "R2209",
    "title": "Noble Tiara",
    "description": "Owners of these don't often mix with each other, because they're already stable.",
    "icon": null,
    "type": null
  },
  {
    "id": "R2210",
    "title": "All Folks Hat",
    "description": "As close to \"one size fits all\" as fantasy headwear can be.",
    "icon": null,
    "type": null
  },
  {
    "id": "R2301",
    "title": "Bandit Mask",
    "description": "The perfect disguise for robbing trains.",
    "icon": null,
    "type": null
  },
  {
    "id": "R2302",
    "title": "Hidden Mask",
    "description": "It matches your complexion perfectly.",
    "icon": null,
    "type": null
  },
  {
    "id": "R2303",
    "title": "Rubber Mask",
    "description": "Make sure to put the lotion on your skin before wearing this mask again.",
    "icon": null,
    "type": null
  },
  {
    "id": "R2304",
    "title": "Cucumber Mask",
    "description": "Put it into a jar with vinegar and salt to create a tasty snack.",
    "icon": null,
    "type": null
  },
  {
    "id": "R2305",
    "title": "Coffee Mask",
    "description": "Seemingly addictive, but comes with strange digestive complications.",
    "icon": null,
    "type": null
  },
  {
    "id": "R2306",
    "title": "Pumpkin Mask",
    "description": "Especially popular in autumn with Basic Wand users.",
    "icon": null,
    "type": null
  },
  {
    "id": "R2307",
    "title": "Stone Mask",
    "description": "The eyes in this mask seem droopy, and a little bloodshot.",
    "icon": null,
    "type": null
  },
  {
    "id": "R2308",
    "title": "Oxygen Mask",
    "description": "Highly flammable.  Proceed with caution.",
    "icon": null,
    "type": null
  },
  {
    "id": "R2309",
    "title": "Spoopy Mask",
    "description": "Somehow funny, and spooky, all at the same time, like a comedy about a ghost.",
    "icon": null,
    "type": null
  },
  {
    "id": "R2310",
    "title": "Volto Mask",
    "description": "Use this mask to find out exactly where the rainbow ends.",
    "icon": null,
    "type": null
  },
  {
    "id": "R3101",
    "title": "New Gauntlets",
    "description": "Fresh from the forge, so treat them right.",
    "icon": null,
    "type": null
  },
  {
    "id": "R3102",
    "title": "Shiny Gauntlets",
    "description": "Almost mirror-like, adventurers often confuse their enemies wearing these.",
    "icon": null,
    "type": null
  },
  {
    "id": "R3103",
    "title": "Plain Gauntlets",
    "description": "The exact opposite of The Everything Gauntlet.",
    "icon": null,
    "type": null
  },
  {
    "id": "R3104",
    "title": "Pristine Gauntlets",
    "description": "These gauntlets have never been touched, until now.  ",
    "icon": null,
    "type": null
  },
  {
    "id": "R3105",
    "title": "Challenge Gauntlets",
    "description": "Legend states that these mythical gauntlets are awarded to dragon raiders and cheese hoarders.",
    "icon": null,
    "type": null
  },
  {
    "id": "R3106",
    "title": "Fancy Gauntlets",
    "description": "For some reason, there's a spot for a gem on the thumb.  That's an odd choice.",
    "icon": null,
    "type": null
  },
  {
    "id": "R3107",
    "title": "Old Gauntlets",
    "description": "Particularly helpful when your wizards need food badly.",
    "icon": null,
    "type": null
  },
  {
    "id": "R3108",
    "title": "Dark Gauntlets",
    "description": "The color of these gauntlets baffle smiths and armorcrafters to this day.",
    "icon": null,
    "type": null
  },
  {
    "id": "R3109",
    "title": "Dandy Gauntlets",
    "description": "Often worn by process servers to deliver copyright disputes.",
    "icon": null,
    "type": null
  },
  {
    "id": "R3110",
    "title": "Cool Gauntlets",
    "description": "The top prize awarded to record holders for breaking misunderstood records.",
    "icon": null,
    "type": null
  },
  {
    "id": "R3201",
    "title": "Gardening Gloves",
    "description": "The thumbs are green, as you would expect.",
    "icon": null,
    "type": null
  },
  {
    "id": "R3202",
    "title": "Running Gloves",
    "description": "Chapped hands are a real problem, and these are the perfect solution.",
    "icon": null,
    "type": null
  },
  {
    "id": "R3203",
    "title": "Fighting Gloves",
    "description": "Ergonomically designed so you can snap while you sing.",
    "icon": null,
    "type": null
  },
  {
    "id": "R3204",
    "title": "Cleaning Gloves",
    "description": "Works great for scrubbing sinks or avoiding the hoi polloi.",
    "icon": null,
    "type": null
  },
  {
    "id": "R3205",
    "title": "Punching Gloves",
    "description": "The knuckles are padded with brass, which seems counterintuitive.",
    "icon": null,
    "type": null
  },
  {
    "id": "R3206",
    "title": "Hugging Gloves",
    "description": "Politicians wear these so that they don't actually have to touch the great unwashed.",
    "icon": null,
    "type": null
  },
  {
    "id": "R3207",
    "title": "Dancing Gloves",
    "description": "The fingers of these gloves are detachable, because sure, why not.",
    "icon": null,
    "type": null
  },
  {
    "id": "R3208",
    "title": "Loving Gloves",
    "description": "Ideally speaking, we should all wear gloves before going to bed.",
    "icon": null,
    "type": null
  },
  {
    "id": "R3209",
    "title": "Other Gloves",
    "description": "Named by an architect who had to come up with a last minute change.",
    "icon": null,
    "type": null
  },
  {
    "id": "R3210",
    "title": "Boxing Gloves",
    "description": "These gloves are the traditional gift given to children the day after Christmas.",
    "icon": null,
    "type": null
  },
  {
    "id": "R3301",
    "title": "Hamster Clogs",
    "description": "These wooden shoes are tiny, and have bits of romaine stuck inside.",
    "icon": null,
    "type": null
  },
  {
    "id": "R3302",
    "title": "Mage Moccasins",
    "description": "Staunch magical defenders used these in ancient times.",
    "icon": null,
    "type": null
  },
  {
    "id": "R3303",
    "title": "Druidic Boots",
    "description": "These boots have odd properties that allow it to change form quickly.",
    "icon": null,
    "type": null
  },
  {
    "id": "R3304",
    "title": "Fighting Stilettos",
    "description": "The perfect shoe for date night and stabbing people in the neck.",
    "icon": null,
    "type": null
  },
  {
    "id": "R3305",
    "title": "Bardic Galoshes",
    "description": "Smells like ale, and covered in syrup.",
    "icon": null,
    "type": null
  },
  {
    "id": "R3306",
    "title": "Master Loafers",
    "description": "Frequently worn around the house, they don't often see the light of day.",
    "icon": null,
    "type": null
  },
  {
    "id": "R3307",
    "title": "Foxy Slippers",
    "description": "One of them appears to have a chip.",
    "icon": null,
    "type": null
  },
  {
    "id": "R3308",
    "title": "Hairy Shoes",
    "description": "The best excuse to have a second breakfast.",
    "icon": null,
    "type": null
  },
  {
    "id": "R3309",
    "title": "Lunar Whalers",
    "description": "You aren't sure why, but wearing these makes you feel more energetic.",
    "icon": null,
    "type": null
  },
  {
    "id": "R3310",
    "title": "Jay Walkers",
    "description": "Upon closer inspection, it appears as if the artist has put their name all over these shoes.",
    "icon": null,
    "type": null
  },
  {
    "id": "R4101",
    "title": "Metal Armor",
    "description": "Provides strong protection, but limited mobility.",
    "icon": null,
    "type": null
  },
  {
    "id": "R4102",
    "title": "Metallic Armor",
    "description": "Just make sure you don't get sand in it.",
    "icon": null,
    "type": null
  },
  {
    "id": "R4103",
    "title": "Panther Armor",
    "description": "If this armor were any heavier, adventurers would collapse from the weight.",
    "icon": null,
    "type": null
  },
  {
    "id": "R4104",
    "title": "Slayers Plate",
    "description": "The history of this armor is mired in controversy.",
    "icon": null,
    "type": null
  },
  {
    "id": "R4105",
    "title": "Leaded Zeppelin Hull",
    "description": "Check out the newer version, the Greta Von Hauberk.",
    "icon": null,
    "type": null
  },
  {
    "id": "R4106",
    "title": "A Cool Dark Chainmail",
    "description": "Given the opportunity, you should paint the back in black or really dark grey.",
    "icon": null,
    "type": null
  },
  {
    "id": "R4107",
    "title": "Maidens Plate",
    "description": "Named after a torture device, this armor can cause hearing loss.",
    "icon": null,
    "type": null
  },
  {
    "id": "R4108",
    "title": "Intense Purple Cuirass",
    "description": "Not to be used as a floatation device.  ",
    "icon": null,
    "type": null
  },
  {
    "id": "R4109",
    "title": "Serpent Mail",
    "description": "Oddly useful at car washes.",
    "icon": null,
    "type": null
  },
  {
    "id": "R4110",
    "title": "Heavy Metal Armor",
    "description": "Somehow, this armor only allows one arm through.",
    "icon": null,
    "type": null
  },
  {
    "id": "R4201",
    "title": "Novice Cloak",
    "description": "A simple protective covering.",
    "icon": null,
    "type": null
  },
  {
    "id": "R4202",
    "title": "Apprentice Cloak",
    "description": "Worn by initiates looking to find more steady work.",
    "icon": null,
    "type": null
  },
  {
    "id": "R4203",
    "title": "Practitioner Cloak",
    "description": "It has a protective coating to prevent forest fires and accidental discharge.",
    "icon": null,
    "type": null
  },
  {
    "id": "R4204",
    "title": "Journeyman Cloak",
    "description": "Wandering magi wear it to harness the elements.",
    "icon": null,
    "type": null
  },
  {
    "id": "R4205",
    "title": "Expert Cloak",
    "description": "The most experienced spellcasters wear this cloak with pride.",
    "icon": null,
    "type": null
  },
  {
    "id": "R4206",
    "title": "Frostflinger Cloak",
    "description": "This garment is as cold as ice, but it's a sacrifice worth making for the power it gives.",
    "icon": null,
    "type": null
  },
  {
    "id": "R4207",
    "title": "Stormbringer Cloak",
    "description": "Made from flannel, it is especially deadly in the dry winter air.",
    "icon": null,
    "type": null
  },
  {
    "id": "R4208",
    "title": "Earthslinger Cloak",
    "description": "Comes with a hydrophobic coating, so you can cause destruction in style.",
    "icon": null,
    "type": null
  },
  {
    "id": "R4209",
    "title": "Lifegiver Cloak",
    "description": "It contains many pockets to hide remedies and antidotes for all occasions.",
    "icon": null,
    "type": null
  },
  {
    "id": "R4210",
    "title": "Deathcaller Cloak",
    "description": "Those who wear this cloak should be forewarned: this cloak may be cursed.",
    "icon": null,
    "type": null
  },
  {
    "id": "R4301",
    "title": "Mole Vest",
    "description": "Worn by those who hide in plain sight.",
    "icon": null,
    "type": null
  },
  {
    "id": "R4302",
    "title": "Assassin Vest",
    "description": "This vest allows the wearer to move silently.",
    "icon": null,
    "type": null
  },
  {
    "id": "R4303",
    "title": "Bandit Vest",
    "description": "Has a handy pocket to keep bandanas and knives.",
    "icon": null,
    "type": null
  },
  {
    "id": "R4304",
    "title": "Spy Vest",
    "description": "Also comes in black and white.",
    "icon": null,
    "type": null
  },
  {
    "id": "R4305",
    "title": "Fugitive Vest",
    "description": "Good for those on the run and trying to prove their innocence.",
    "icon": null,
    "type": null
  },
  {
    "id": "R4306",
    "title": "Outlaw Vest",
    "description": "Great for protecting against the elements while in exile.",
    "icon": null,
    "type": null
  },
  {
    "id": "R4307",
    "title": "Grifter Vest",
    "description": "When grifting someone, make sure they aren't broke, or well connected.",
    "icon": null,
    "type": null
  },
  {
    "id": "R4308",
    "title": "Criminal Vest",
    "description": "Designed by a soft spoken judge who understands criminals quite well.",
    "icon": null,
    "type": null
  },
  {
    "id": "R4309",
    "title": "Hitman Vest",
    "description": "Hitperson just doesn't sound right, but it's a gender neutral vest.",
    "icon": null,
    "type": null
  },
  {
    "id": "R4310",
    "title": "Pirate Vest",
    "description": "Contains a special shoulder attachment for parrots to perch on.",
    "icon": null,
    "type": null
  },
  {
    "id": "R5101",
    "title": "Patience",
    "description": "Sometimes the easiest way to win is to wait for your enemy to die.",
    "icon": null,
    "type": null
  },
  {
    "id": "R5102",
    "title": "Faithful Buckler",
    "description": "Seeing is believing, but blocking with this shield doesn't hurt either.",
    "icon": null,
    "type": null
  },
  {
    "id": "R5103",
    "title": "Defiant Targe",
    "description": "This shield will help you hold your ground, even in adverse situations.",
    "icon": null,
    "type": null
  },
  {
    "id": "R5104",
    "title": "Fair Shield",
    "description": "Fairness is okay as long as I get what I want.",
    "icon": null,
    "type": null
  },
  {
    "id": "R5105",
    "title": "Wisdom",
    "description": "Wisdom is knowing not to put tomatoes in a fruit salad.",
    "icon": null,
    "type": null
  },
  {
    "id": "R5106",
    "title": "Generous Blocker",
    "description": "Easily able to cover an adventurer and a half.",
    "icon": null,
    "type": null
  },
  {
    "id": "R5107",
    "title": "Loyal Companion",
    "description": "This shield is lined with fur, so it will keep you warm at night.",
    "icon": null,
    "type": null
  },
  {
    "id": "R5108",
    "title": "Dignity",
    "description": "The most luxurious possession and richest treasure most people will ever have.",
    "icon": null,
    "type": null
  },
  {
    "id": "R5109",
    "title": "Trustworthy Kite",
    "description": "Sometimes the best shield against harm is your own principles.",
    "icon": null,
    "type": null
  },
  {
    "id": "R5110",
    "title": "Truth Teller",
    "description": "One good hit to your enemy's skull should help them give up any secrets.",
    "icon": null,
    "type": null
  },
  {
    "id": "R5301",
    "title": "Stones",
    "description": "Not safe to own in houses made of glass.",
    "icon": null,
    "type": null
  },
  {
    "id": "R5302",
    "title": "Sticks",
    "description": "Don't shove this in your bike spokes.",
    "icon": null,
    "type": null
  },
  {
    "id": "R5303",
    "title": "Words",
    "description": "Use this against yourself before your enemies get the chance.",
    "icon": null,
    "type": null
  },
  {
    "id": "R5304",
    "title": "Shooting Stars",
    "description": "Protect yourself against bag raiders with a handful of these.",
    "icon": null,
    "type": null
  },
  {
    "id": "R5305",
    "title": "Poison Shuriken",
    "description": "A little poison will go a long way, so use it modestly.",
    "icon": null,
    "type": null
  },
  {
    "id": "R5306",
    "title": "Shining Stars",
    "description": "Manages to reflect light, even when covered in blood.",
    "icon": null,
    "type": null
  },
  {
    "id": "R5307",
    "title": "Golden Shuriken",
    "description": "This weapon broke the mold.  Throw for the moon.",
    "icon": null,
    "type": null
  },
  {
    "id": "R5308",
    "title": "Frost Shuriken",
    "description": "Consider it a really sharp chill pill.",
    "icon": null,
    "type": null
  },
  {
    "id": "R5309",
    "title": "Burning Sticks",
    "description": "All it takes is one match to start an explosion.",
    "icon": null,
    "type": null
  },
  {
    "id": "R5310",
    "title": "Heart Seeker",
    "description": "The fastest way to your enemy's heart is through his stomach, so aim for that.",
    "icon": null,
    "type": null
  },
  {
    "id": "R5501",
    "title": "Spells Vol I",
    "description": "An introduction into the wide world of magic.",
    "icon": null,
    "type": null
  },
  {
    "id": "R5502",
    "title": "Spells Vol II",
    "description": "Basic ingredients and techniques commonly used.",
    "icon": null,
    "type": null
  },
  {
    "id": "R5503",
    "title": "Spells Vol IV",
    "description": "Fun stories from former witches and warlocks.",
    "icon": null,
    "type": null
  },
  {
    "id": "R5504",
    "title": "Earthshaping and You",
    "description": "How to make your enemies dirty while staying squeaky clean.",
    "icon": null,
    "type": null
  },
  {
    "id": "R5505",
    "title": "Pyromania: A Love Story",
    "description": "How to make long distance relationships with magma elementals work.",
    "icon": null,
    "type": null
  },
  {
    "id": "R5506",
    "title": "Great Hamster Vol XXI",
    "description": [
      "New for Vol XXI: a special section on salads and croutons",
      ""
    ],
    "icon": null,
    "type": null
  },
  {
    "id": "R5507",
    "title": "Nal'Dur's Diary",
    "description": "I'm so upset.  How can I be expected to end the world when I can't even get Tommy to notice me?",
    "icon": null,
    "type": null
  },
  {
    "id": "R5508",
    "title": "Cauldroning 101",
    "description": "A deep dive into best practices, but it is so dense most people don't know who the author is.",
    "icon": null,
    "type": null
  },
  {
    "id": "R5509",
    "title": "Secret Streams",
    "description": "Upon further review, it looks like a manual about divining rods.",
    "icon": null,
    "type": null
  },
  {
    "id": "R5510",
    "title": "Efficient Spells 102",
    "description": "The final volume from an outcast former expert.",
    "icon": null,
    "type": null
  },
  {
    "id": "R6201",
    "title": "Lactuca",
    "description": "The beloved pendant of vegetarians and vegans.",
    "icon": null,
    "type": null
  },
  {
    "id": "R6202",
    "title": "Gelata Eros",
    "description": "A little sticky, and a little nutty, but it makes everyone jealous.",
    "icon": null,
    "type": null
  },
  {
    "id": "R6203",
    "title": "Comitatus",
    "description": "Created in fertile farmland where great adventures seem to begin.",
    "icon": null,
    "type": null
  },
  {
    "id": "R6204",
    "title": "Tacet Gladio",
    "description": "Walk softly, and carry a big stick to impale your adversaries with.",
    "icon": null,
    "type": null
  },
  {
    "id": "R6205",
    "title": "Ostium Amici",
    "description": "Manly men in northern regions are particularly suited for this pendant.",
    "icon": null,
    "type": null
  },
  {
    "id": "R6206",
    "title": "Ignis Pullum",
    "description": "Contains the feather of an resurrected avian creature.",
    "icon": null,
    "type": null
  },
  {
    "id": "R6207",
    "title": "Folium Strennus",
    "description": "Used by only the most impassioned adventurers.",
    "icon": null,
    "type": null
  },
  {
    "id": "R6208",
    "title": "Magicae Criceta",
    "description": "This pendant looks good, and works amazingly well.",
    "icon": null,
    "type": null
  },
  {
    "id": "R6209",
    "title": "Inpulsa Sciurus",
    "description": "Wearing this trinket bestows a sense of pride and accomplishment.",
    "icon": null,
    "type": null
  },
  {
    "id": "R6210",
    "title": "Adipem Pater",
    "description": "If this pendant could lose some weight, it would be far more useful.",
    "icon": null,
    "type": null
  },
  {
    "id": "R6301",
    "title": "Soldier Ring",
    "description": "The soldiers soldered this ring themselves.",
    "icon": null,
    "type": null
  },
  {
    "id": "R6302",
    "title": "Mercenary Ring",
    "description": "This ring signifies that the wearer holds no allegiances.",
    "icon": null,
    "type": null
  },
  {
    "id": "R6303",
    "title": "Chaplain Ring",
    "description": "Adorned with certain etchings that make it unmistakable.",
    "icon": null,
    "type": null
  },
  {
    "id": "R6304",
    "title": "General Ring",
    "description": "Gifted to the most prestigious of generals upon retirement.",
    "icon": null,
    "type": null
  },
  {
    "id": "R6305",
    "title": "Tactical Ring",
    "description": "Might be a decoder ring, but it's hard to tell.",
    "icon": null,
    "type": null
  },
  {
    "id": "R6306",
    "title": "Paladin Ring",
    "description": "Contains a small amount of holy water, just in case.",
    "icon": null,
    "type": null
  },
  {
    "id": "R6307",
    "title": "Hunter Ring",
    "description": "Worn to show prowess and cunning in battle.",
    "icon": null,
    "type": null
  },
  {
    "id": "R6308",
    "title": "Trapper Ring",
    "description": "Signifies a commitment to a difficult and taxing profession.",
    "icon": null,
    "type": null
  },
  {
    "id": "R6309",
    "title": "Berserker Ring",
    "description": "The love for this ring is like a ticking clock.",
    "icon": null,
    "type": null
  },
  {
    "id": "R6310",
    "title": "Marksman Ring",
    "description": "Holds some secrets shown to be invaluable to the most skilled sharpshooters.",
    "icon": null,
    "type": null
  },
  {
    "id": "R6501",
    "title": "Leather Belt",
    "description": "Keeps your pants up.",
    "icon": null,
    "type": null
  },
  {
    "id": "R6502",
    "title": "Timing Belt",
    "description": "Make sure to wear this belt at just the right moment.",
    "icon": null,
    "type": null
  },
  {
    "id": "R6503",
    "title": "Rodeo Belt",
    "description": "Awarded to the best in competition.",
    "icon": null,
    "type": null
  },
  {
    "id": "R6504",
    "title": "Rust Belt",
    "description": "Once worn by skilled laborers, many years ago.",
    "icon": null,
    "type": null
  },
  {
    "id": "R6505",
    "title": "Cowboy Belt",
    "description": "The gawdy buckle is supposed to signify wealth.",
    "icon": null,
    "type": null
  },
  {
    "id": "R6506",
    "title": "Flat Belt",
    "description": "This belt has been left out in the open for way too long.",
    "icon": null,
    "type": null
  },
  {
    "id": "R6507",
    "title": "Fan Belt",
    "description": "For some reason, this belt is constantly oscillating.",
    "icon": null,
    "type": null
  },
  {
    "id": "R6508",
    "title": "Formal Belt",
    "description": "Matches perfectly with business socks, for business time.",
    "icon": null,
    "type": null
  },
  {
    "id": "R6509",
    "title": "Conveyor Belt",
    "description": "The leather in this belt was orginally used in a pulley system.",
    "icon": null,
    "type": null
  },
  {
    "id": "R6510",
    "title": "Extra Belt",
    "description": "This belt is just way over the top.  Entirely too much going on.",
    "icon": null,
    "type": null
  },
  {
    "id": "R99410",
    "title": "Magical Desynth",
    "description": "Harvest the magical energy from your rare items.",
    "icon": null,
    "type": null
  },
  {
    "id": "R99110",
    "title": "Bank",
    "description": "Store your precious keepsakes here.",
    "icon": null,
    "type": null
  },
  {
    "id": "R99210",
    "title": "Fuse Hut",
    "description": "Combine items to make better stuff.",
    "icon": null,
    "type": null
  },
  {
    "id": "R99310",
    "title": "The Forgery",
    "description": "All or nothing, baby.",
    "icon": null,
    "type": null
  },
  {
    "id": "R99510",
    "title": "Fortune Teller",
    "description": "Hopefully she shows up.",
    "icon": null,
    "type": null
  },
  {
    "id": "R99610",
    "title": "Tinker Hut",
    "description": "Chew some rocks and make some stuff.",
    "icon": null,
    "type": null
  },
  {
    "id": "R99710",
    "title": "Monster Hall",
    "description": "A catalog of monsters you've seen",
    "icon": null,
    "type": null
  },
  {
    "id": "R90001",
    "title": "Philosopher's Trinket",
    "description": "This trinket provides critical thinking skills and a predisposition to murders by train.",
    "icon": null,
    "type": null
  },
  {
    "id": "R90002",
    "title": "Theatrical Trinket",
    "description": "All who doth adorn their personage with yon trinket will acquire expert knowledgeth in the theatricalth arths.",
    "icon": null,
    "type": null
  },
  {
    "id": "R90003",
    "title": "Engineer's Trinket",
    "description": "Use this trinket.  It will make your skills better.  End of flavor text.",
    "icon": null,
    "type": null
  },
  {
    "id": "W001",
    "title": "Oren",
    "description": "Oren comes from a long line of miners and specializes in gathering Ore.",
    "icon": null,
    "type": null
  },
  {
    "id": "W002",
    "title": "Eryn",
    "description": "Eryn carefully chooses which trees to chop down to produce Wood.",
    "icon": null,
    "type": null
  },
  {
    "id": "W003",
    "title": "Herbie",
    "description": "Herbie is a fledgling botanist and spends his days collecting Herbs.",
    "icon": null,
    "type": null
  },
  {
    "id": "W004",
    "title": "Lakur",
    "description": "Lakur is a skilled hunter and earns her living by producing Leather.",
    "icon": null,
    "type": null
  },
  {
    "id": "W005",
    "title": "Harmony",
    "description": "Harmony has a black market supplier, and expertly refines Bone.",
    "icon": null,
    "type": null
  },
  {
    "id": "W006",
    "title": "Frederik",
    "description": "Frederik hopes to become a designer, but for now, creates Fabric.",
    "icon": null,
    "type": null
  },
  {
    "id": "W007",
    "title": "Magnolia",
    "description": "Magnolia was taught by her mother to produce high quality Steel.",
    "icon": null,
    "type": null
  },
  {
    "id": "W008",
    "title": "Sylvester",
    "description": "Sylvester relies on reputable ore traders to smelts his Silver.",
    "icon": null,
    "type": null
  },
  {
    "id": "W009",
    "title": "Pippa",
    "description": "Pippa has excellent attention to detail, and it shows in her Paper.",
    "icon": null,
    "type": null
  },
  {
    "id": "W010",
    "title": "Manny",
    "description": "Manny has perfected a very delicate technique to gather Mana.",
    "icon": null,
    "type": null
  },
  {
    "id": "W101",
    "title": "Hardy",
    "description": "Hardy has two passions: being a good big brother, and mining Ore.",
    "icon": null,
    "type": null
  },
  {
    "id": "W102",
    "title": "Wendy",
    "description": "Wendy is trying to emulate Eryn, and the second step is making Wood.",
    "icon": null,
    "type": null
  },
  {
    "id": "W103",
    "title": "Blossom",
    "description": "Blossom loves being outdoors, and enjoys her time collecting Herbs.",
    "icon": null,
    "type": null
  },
  {
    "id": "W104",
    "title": "Rocky",
    "description": "Rocky finds it's best not to think too hard about how he makes Leather.",
    "icon": null,
    "type": null
  },
  {
    "id": "W105",
    "title": "Floyd",
    "description": "Floyd has a special, one-of-a-kind relationship with Bone.",
    "icon": null,
    "type": null
  },
  {
    "id": "W106",
    "title": "Tricia",
    "description": "Tricia is a hard-working student, hoping to learn all she can about Fabric.",
    "icon": null,
    "type": null
  },
  {
    "id": "W107",
    "title": "Remington",
    "description": "Remington works very hard, providing only the highest quality Steel.",
    "icon": null,
    "type": null
  },
  {
    "id": "W108",
    "title": "Renae",
    "description": "Renae enjoys getting her hands dirty when she processes Silver.",
    "icon": null,
    "type": null
  },
  {
    "id": "W109",
    "title": "Paula",
    "description": "Paula is an excellent understudy, and is getting better at making Paper.",
    "icon": null,
    "type": null
  },
  {
    "id": "W110",
    "title": "Jewel",
    "description": "Jewel doesn't enjoy her job, but her bills get paid by gathering Mana.",
    "icon": null,
    "type": null
  },
  {
    "id": "WN001",
    "title": "Oren",
    "description": "Oren comes from a long line of crafters.",
    "icon": null,
    "type": null
  },
  {
    "id": "WN002",
    "title": "Eryn",
    "description": "Eryn carefully chooses which materials to use.",
    "icon": null,
    "type": null
  },
  {
    "id": "WN003",
    "title": "Herbie",
    "description": "Herbie is a fledgling botanist in his spare time.",
    "icon": null,
    "type": null
  },
  {
    "id": "WN004",
    "title": "Lakur",
    "description": "Lakur is a skilled hunter and is proud to use her own products.",
    "icon": null,
    "type": null
  },
  {
    "id": "WN101",
    "title": "Tiny",
    "description": "Tiny is a hard-working student, hoping to learn all he can.",
    "icon": null,
    "type": null
  },
  {
    "id": "WN102",
    "title": "Crash",
    "description": "Crash relies on reputable traders for raw materials.",
    "icon": null,
    "type": null
  },
  {
    "id": "WN103",
    "title": "Titan",
    "description": "Titan often finds himself moderating disputes in the shop.",
    "icon": null,
    "type": null
  },
  {
    "id": "WN104",
    "title": "Smash",
    "description": "Smash has excellent attention to detail, and it shows.",
    "icon": null,
    "type": null
  },
  {
    "id": "WN201",
    "title": "Francis",
    "description": "Francis wants to be the very best, the best that ever was.",
    "icon": null,
    "type": null
  },
  {
    "id": "WN202",
    "title": "Squeaks",
    "description": "Squeaks is shy around new customers, but is very loyal.",
    "icon": null,
    "type": null
  },
  {
    "id": "WN203",
    "title": "Renae",
    "description": "Renae was taught by her mother to produce high quality goods.",
    "icon": null,
    "type": null
  },
  {
    "id": "WN204",
    "title": "Tawny",
    "description": "Tawny secretly moonlights as a dancer after business hours.",
    "icon": null,
    "type": null
  },
  {
    "id": "WN301",
    "title": "Gilbert",
    "description": "Gilbert is an excellent understudy with a bright future.",
    "icon": null,
    "type": null
  },
  {
    "id": "WN302",
    "title": "Gillian",
    "description": "Gillian has a underground black market supplier.",
    "icon": null,
    "type": null
  },
  {
    "id": "WN303",
    "title": "Gilfred",
    "description": "Gilfred hopes to become a designer one day.",
    "icon": null,
    "type": null
  },
  {
    "id": "WN304",
    "title": "Gilda",
    "description": "Gilda doesn't enjoy her job, but her bills get paid on time.",
    "icon": null,
    "type": null
  },
  {
    "id": "gold_value",
    "title": "#value# Gold",
    "description": "The amount of gold this recipe is worth.",
    "icon": "/images/resources/M001.png",
    "type": "value"
  }
]